dirac_hashes-0.1.3.dist-info/licenses/LICENSE
quantum_hash/__init__.py
quantum_hash/dirac.py
quantum_hash/core/__init__.py
quantum_hash/core/grover.py
quantum_hash/core/improved_hash.py
quantum_hash/core/shor.py
quantum_hash/core/simd_optimized.py
quantum_hash/kem/__init__.py
quantum_hash/kem/example.py
quantum_hash/kem/kyber.py
quantum_hash/kem/test_kyber.py
quantum_hash/signatures/__init__.py
quantum_hash/signatures/dilithium.py
quantum_hash/signatures/kyber.py
quantum_hash/signatures/lamport.py
quantum_hash/signatures/sphincs.py
quantum_hash/tests/__init__.py
quantum_hash/tests/test_basic.py
quantum_hash/utils/__init__.py
quantum_hash/utils/hash.py
quantum_hash/utils/keys.py
dirac_hashes-0.1.3.dist-info/METADATA
dirac_hashes-0.1.3.dist-info/WHEEL
dirac_hashes-0.1.3.dist-info/top_level.txt
dirac_hashes-0.1.3.dist-info/RECORD
