Metadata-Version: 2.4
Name: dirac-hashes
Version: 0.1.3
Summary: Quantum-resistant hash functions and post-quantum cryptography for blockchain
Home-page: https://github.com/mk0dz/dirac-hashes
Author: mk0dz
Author-email: mk0dz <Mukulpal108@hotmail.com>
License: MIT
Project-URL: Homepage, https://github.com/mk0dz/dirac-hashes
Project-URL: Documentation, https://dirac-hashes.vercel.app/
Project-URL: Repository, https://github.com/mk0dz/dirac-hashes.git
Project-URL: Bug Tracker, https://github.com/mk0dz/dirac-hashes/issues
Keywords: quantum,cryptography,hash,signatures,blockchain
Classifier: Programming Language :: Python :: 3
Classifier: Programming Language :: Python :: 3.7
Classifier: Programming Language :: Python :: 3.8
Classifier: Programming Language :: Python :: 3.9
Classifier: Programming Language :: Python :: 3.10
Classifier: License :: OSI Approved :: MIT License
Classifier: Operating System :: OS Independent
Classifier: Development Status :: 3 - Alpha
Classifier: Intended Audience :: Developers
Classifier: Topic :: Security :: Cryptography
Classifier: Topic :: Software Development :: Libraries :: Python Modules
Requires-Python: >=3.7
License-File: LICENSE
Dynamic: author
Dynamic: home-page
Dynamic: license-file
Dynamic: requires-python
